{
  "edges": [
    {
      "id": "Import CSV 1 output Rename table 1 b",
      "source": "Import CSV 1",
      "sourceHandle": "output",
      "target": "Rename table 1",
      "targetHandle": "b"
    },
    {
      "id": "Rename table 1 output Join tables 1 bundle_a",
      "source": "Rename table 1",
      "sourceHandle": "output",
      "target": "Join tables 1",
      "targetHandle": "bundle_a"
    },
    {
      "id": "Import CSV 2 output Rename table 2 b",
      "source": "Import CSV 2",
      "sourceHandle": "output",
      "target": "Rename table 2",
      "targetHandle": "b"
    },
    {
      "id": "Rename table 2 output Join tables 1 bundle_b",
      "source": "Rename table 2",
      "sourceHandle": "output",
      "target": "Join tables 1",
      "targetHandle": "bundle_b"
    },
    {
      "id": "Derive property 1 output Add rank attribute 1 b",
      "source": "Derive property 1",
      "sourceHandle": "output",
      "target": "Add rank attribute 1",
      "targetHandle": "b"
    },
    {
      "id": "Join tables 1 output Vector from attribute pair 1 b",
      "source": "Join tables 1",
      "sourceHandle": "output",
      "target": "Vector from attribute pair 1",
      "targetHandle": "b"
    },
    {
      "id": "Vector from attribute pair 1 output Vector from attribute pair 2 b",
      "source": "Vector from attribute pair 1",
      "sourceHandle": "output",
      "target": "Vector from attribute pair 2",
      "targetHandle": "b"
    },
    {
      "id": "Vector from attribute pair 2 output Derive property 1 b",
      "source": "Vector from attribute pair 2",
      "sourceHandle": "output",
      "target": "Derive property 1",
      "targetHandle": "b"
    },
    {
      "id": "Add rank attribute 1 output Derive property 2 b",
      "source": "Add rank attribute 1",
      "sourceHandle": "output",
      "target": "Derive property 2",
      "targetHandle": "b"
    },
    {
      "id": "Filter with formula 1 output Filter with formula 2 b",
      "source": "Filter with formula 1",
      "sourceHandle": "output",
      "target": "Filter with formula 2",
      "targetHandle": "b"
    },
    {
      "id": "Derive property 2 output Connect nodes on attribute 1 b",
      "source": "Derive property 2",
      "sourceHandle": "output",
      "target": "Connect nodes on attribute 1",
      "targetHandle": "b"
    },
    {
      "id": "Connect nodes on attribute 1 output Filter with formula 1 b",
      "source": "Connect nodes on attribute 1",
      "sourceHandle": "output",
      "target": "Filter with formula 1",
      "targetHandle": "b"
    }
  ],
  "env": "LynxKite Graph Analytics",
  "execution_options": {},
  "nodes": [
    {
      "data": {
        "__execution_delay": 0.0,
        "collapsed": null,
        "display": null,
        "error": null,
        "expanded_height": null,
        "input_metadata": [],
        "message": null,
        "meta": null,
        "op_id": "File operations > Import CSV",
        "output_metadata": [
          {
            "dataframes": {
              "records": {
                "columns": [
                  "event_subtype",
                  "event_type",
                  "match_id",
                  "player_id",
                  "ts",
                  "x_abs",
                  "x_rel",
                  "y_abs",
                  "y_rel"
                ],
                "key": "records",
                "length": 125463.0
              }
            },
            "other": {},
            "relations": []
          }
        ],
        "params": {
          "columns": "<from file>",
          "filename": " https://storage.googleapis.com/lynxkite_public_data/pzubcsek/Soccer/events.csv",
          "separator": "<auto>"
        },
        "status": "done",
        "telemetry": null,
        "title": "Import CSV"
      },
      "height": 315.0,
      "id": "Import CSV 1",
      "position": {
        "x": 560.0,
        "y": 334.0
      },
      "type": "basic",
      "width": 315.0
    },
    {
      "data": {
        "__execution_delay": 0.0,
        "collapsed": null,
        "display": null,
        "error": null,
        "expanded_height": null,
        "input_metadata": [],
        "message": null,
        "meta": null,
        "op_id": "File operations > Import CSV",
        "output_metadata": [
          {
            "dataframes": {
              "records": {
                "columns": [
                  "id",
                  "name",
                  "team_name"
                ],
                "key": "records",
                "length": 602.0
              }
            },
            "other": {},
            "relations": []
          }
        ],
        "params": {
          "columns": "<from file>",
          "filename": "https://storage.googleapis.com/lynxkite_public_data/pzubcsek/Soccer/players.csv",
          "separator": "<auto>"
        },
        "status": "done",
        "telemetry": null,
        "title": "Import CSV"
      },
      "height": 315.0,
      "id": "Import CSV 2",
      "position": {
        "x": 577.5,
        "y": 711.0
      },
      "type": "basic",
      "width": 315.0
    },
    {
      "data": {
        "__execution_delay": 0.0,
        "collapsed": null,
        "display": null,
        "error": null,
        "expanded_height": null,
        "input_metadata": [
          {
            "dataframes": {
              "events": {
                "columns": [
                  "event_subtype",
                  "event_type",
                  "match_id",
                  "player_id",
                  "ts",
                  "x_abs",
                  "x_rel",
                  "y_abs",
                  "y_rel"
                ],
                "key": "events",
                "length": 125463.0
              }
            },
            "other": {},
            "relations": []
          },
          {
            "dataframes": {
              "players": {
                "columns": [
                  "id",
                  "name",
                  "team_name"
                ],
                "key": "players",
                "length": 602.0
              }
            },
            "other": {},
            "relations": []
          }
        ],
        "message": null,
        "meta": null,
        "op_id": "Table operations > Join tables",
        "output_metadata": [
          {
            "dataframes": {
              "merged": {
                "columns": [
                  "event_subtype",
                  "event_type",
                  "id",
                  "match_id",
                  "name",
                  "player_id",
                  "team_name",
                  "ts",
                  "x_abs",
                  "x_rel",
                  "y_abs",
                  "y_rel"
                ],
                "key": "merged",
                "length": 125463.0
              }
            },
            "other": {},
            "relations": []
          }
        ],
        "params": {
          "join_type": "inner",
          "left_on": "player_id",
          "on_column": "",
          "right_on": "id",
          "suffixes": "_a,_b",
          "table_a": "events",
          "table_b": "players"
        },
        "status": "done",
        "telemetry": null,
        "title": "Join tables"
      },
      "height": 315.0,
      "id": "Join tables 1",
      "position": {
        "x": 1422.2479228512086,
        "y": 592.317816042828
      },
      "type": "basic",
      "width": 315.0
    },
    {
      "data": {
        "__execution_delay": 0.0,
        "collapsed": null,
        "display": null,
        "error": null,
        "expanded_height": null,
        "input_metadata": [
          {
            "dataframes": {
              "records": {
                "columns": [
                  "event_subtype",
                  "event_type",
                  "match_id",
                  "player_id",
                  "ts",
                  "x_abs",
                  "x_rel",
                  "y_abs",
                  "y_rel"
                ],
                "key": "records",
                "length": 125463.0
              }
            },
            "other": {},
            "relations": []
          }
        ],
        "message": null,
        "meta": null,
        "op_id": "Table operations > Rename table",
        "output_metadata": [
          {
            "dataframes": {
              "events": {
                "columns": [
                  "event_subtype",
                  "event_type",
                  "match_id",
                  "player_id",
                  "ts",
                  "x_abs",
                  "x_rel",
                  "y_abs",
                  "y_rel"
                ],
                "key": "events",
                "length": 125463.0
              }
            },
            "other": {},
            "relations": []
          }
        ],
        "params": {
          "new_name": "events",
          "old_name": "records"
        },
        "status": "done",
        "telemetry": null,
        "title": "Rename table"
      },
      "height": 315.0,
      "id": "Rename table 1",
      "position": {
        "x": 1005.0272616400537,
        "y": 376.5247944134059
      },
      "type": "basic",
      "width": 315.0
    },
    {
      "data": {
        "__execution_delay": 0.0,
        "collapsed": null,
        "display": null,
        "error": null,
        "expanded_height": null,
        "input_metadata": [
          {
            "dataframes": {
              "records": {
                "columns": [
                  "id",
                  "name",
                  "team_name"
                ],
                "key": "records",
                "length": 602.0
              }
            },
            "other": {},
            "relations": []
          }
        ],
        "message": null,
        "meta": null,
        "op_id": "Table operations > Rename table",
        "output_metadata": [
          {
            "dataframes": {
              "players": {
                "columns": [
                  "id",
                  "name",
                  "team_name"
                ],
                "key": "players",
                "length": 602.0
              }
            },
            "other": {},
            "relations": []
          }
        ],
        "params": {
          "new_name": "players",
          "old_name": "records"
        },
        "status": "done",
        "telemetry": null,
        "title": "Rename table"
      },
      "height": 315.0,
      "id": "Rename table 2",
      "position": {
        "x": 985.0406431389206,
        "y": 712.9662058491475
      },
      "type": "basic",
      "width": 315.0
    },
    {
      "data": {
        "__execution_delay": 0.0,
        "collapsed": null,
        "display": null,
        "error": null,
        "expanded_height": null,
        "input_metadata": [
          {
            "dataframes": {
              "merged": {
                "columns": [
                  "event_subtype",
                  "event_type",
                  "field_pos_abs",
                  "field_pos_rel",
                  "id",
                  "match_id",
                  "name",
                  "player_id",
                  "team_name",
                  "ts",
                  "x_abs",
                  "x_rel",
                  "y_abs",
                  "y_rel"
                ],
                "key": "merged",
                "length": 125463.0
              }
            },
            "other": {},
            "relations": []
          }
        ],
        "message": null,
        "meta": null,
        "op_id": "Table operations > Derive property",
        "output_metadata": [
          {
            "dataframes": {
              "merged": {
                "columns": [
                  "event_subtype",
                  "event_type",
                  "field_pos_abs",
                  "field_pos_rel",
                  "id",
                  "match_event",
                  "match_id",
                  "name",
                  "player_id",
                  "team_name",
                  "ts",
                  "x_abs",
                  "x_rel",
                  "y_abs",
                  "y_rel"
                ],
                "key": "merged",
                "length": 125463.0
              }
            },
            "other": {},
            "relations": []
          }
        ],
        "params": {
          "formula": "match_event = match_id + 1-(1/(1 + ts))",
          "table_name": "merged"
        },
        "status": "done",
        "telemetry": null,
        "title": "Derive property"
      },
      "height": 315.0,
      "id": "Derive property 1",
      "position": {
        "x": 2919.1881118571414,
        "y": 636.7732220738064
      },
      "type": "basic",
      "width": 315.0
    },
    {
      "data": {
        "__execution_delay": 0.0,
        "collapsed": null,
        "display": null,
        "error": null,
        "expanded_height": null,
        "input_metadata": [
          {
            "dataframes": {
              "merged": {
                "columns": [
                  "event_subtype",
                  "event_type",
                  "field_pos_abs",
                  "field_pos_rel",
                  "id",
                  "match_event",
                  "match_id",
                  "name",
                  "player_id",
                  "team_name",
                  "ts",
                  "x_abs",
                  "x_rel",
                  "y_abs",
                  "y_rel"
                ],
                "key": "merged",
                "length": 125463.0
              }
            },
            "other": {},
            "relations": []
          }
        ],
        "message": null,
        "meta": null,
        "op_id": "Table operations > Add rank attribute",
        "output_metadata": [
          {
            "dataframes": {
              "merged": {
                "columns": [
                  "event_subtype",
                  "event_type",
                  "field_pos_abs",
                  "field_pos_rel",
                  "id",
                  "match_event",
                  "match_id",
                  "matchevent_seq",
                  "name",
                  "player_id",
                  "team_name",
                  "ts",
                  "x_abs",
                  "x_rel",
                  "y_abs",
                  "y_rel"
                ],
                "key": "merged",
                "length": 125463.0
              }
            },
            "other": {},
            "relations": []
          }
        ],
        "params": {
          "order": "ascending",
          "rank_name": "matchevent_seq",
          "table_column": [
            "merged",
            "match_event"
          ]
        },
        "status": "done",
        "telemetry": null,
        "title": "Add rank attribute"
      },
      "height": 411.0,
      "id": "Add rank attribute 1",
      "position": {
        "x": 3363.2016534756135,
        "y": 588.5596353775063
      },
      "type": "basic",
      "width": 373.0
    },
    {
      "data": {
        "__execution_delay": 0.0,
        "collapsed": null,
        "display": null,
        "error": null,
        "expanded_height": null,
        "input_metadata": [
          {
            "dataframes": {
              "merged": {
                "columns": [
                  "event_subtype",
                  "event_type",
                  "field_pos_abs",
                  "id",
                  "match_id",
                  "name",
                  "player_id",
                  "team_name",
                  "ts",
                  "x_abs",
                  "x_rel",
                  "y_abs",
                  "y_rel"
                ],
                "key": "merged",
                "length": 125463.0
              }
            },
            "other": {},
            "relations": []
          }
        ],
        "message": null,
        "meta": null,
        "op_id": "Table operations > Vector from attribute pair",
        "output_metadata": [
          {
            "dataframes": {
              "merged": {
                "columns": [
                  "event_subtype",
                  "event_type",
                  "field_pos_abs",
                  "id",
                  "match_id",
                  "name",
                  "player_id",
                  "team_name",
                  "ts",
                  "x_abs",
                  "x_rel",
                  "y_abs",
                  "y_rel"
                ],
                "key": "merged",
                "length": 125463.0
              }
            },
            "other": {},
            "relations": []
          }
        ],
        "params": {
          "attribute1": "x_abs",
          "attribute2": "y_abs",
          "new_name": "field_pos_abs",
          "table_name": "merged"
        },
        "status": "done",
        "telemetry": null,
        "title": "Vector from attribute pair"
      },
      "height": 315.0,
      "id": "Vector from attribute pair 1",
      "position": {
        "x": 2007.1919474022443,
        "y": 630.8255877291465
      },
      "type": "basic",
      "width": 315.0
    },
    {
      "data": {
        "__execution_delay": 0.0,
        "collapsed": null,
        "display": null,
        "error": null,
        "expanded_height": null,
        "input_metadata": [
          {
            "dataframes": {
              "merged": {
                "columns": [
                  "event_subtype",
                  "event_type",
                  "field_pos_abs",
                  "field_pos_rel",
                  "id",
                  "match_id",
                  "name",
                  "player_id",
                  "team_name",
                  "ts",
                  "x_abs",
                  "x_rel",
                  "y_abs",
                  "y_rel"
                ],
                "key": "merged",
                "length": 125463.0
              }
            },
            "other": {},
            "relations": []
          }
        ],
        "message": null,
        "meta": null,
        "op_id": "Table operations > Vector from attribute pair",
        "output_metadata": [
          {
            "dataframes": {
              "merged": {
                "columns": [
                  "event_subtype",
                  "event_type",
                  "field_pos_abs",
                  "field_pos_rel",
                  "id",
                  "match_id",
                  "name",
                  "player_id",
                  "team_name",
                  "ts",
                  "x_abs",
                  "x_rel",
                  "y_abs",
                  "y_rel"
                ],
                "key": "merged",
                "length": 125463.0
              }
            },
            "other": {},
            "relations": []
          }
        ],
        "params": {
          "attribute1": "x_rel",
          "attribute2": "y_rel",
          "new_name": "field_pos_rel",
          "table_name": "merged"
        },
        "status": "done",
        "telemetry": null,
        "title": "Vector from attribute pair"
      },
      "height": 315.0,
      "id": "Vector from attribute pair 2",
      "position": {
        "x": 2470.0401008656527,
        "y": 635.9935192808532
      },
      "type": "basic",
      "width": 315.0
    },
    {
      "data": {
        "__execution_delay": 0.0,
        "collapsed": null,
        "display": null,
        "error": null,
        "expanded_height": null,
        "input_metadata": [
          {
            "dataframes": {
              "merged": {
                "columns": [
                  "event_subtype",
                  "event_type",
                  "field_pos_abs",
                  "field_pos_rel",
                  "id",
                  "match_event",
                  "match_id",
                  "matchevent_seq",
                  "name",
                  "player_id",
                  "team_name",
                  "ts",
                  "x_abs",
                  "x_rel",
                  "y_abs",
                  "y_rel"
                ],
                "key": "merged",
                "length": 125463.0
              }
            },
            "other": {},
            "relations": []
          }
        ],
        "message": null,
        "meta": null,
        "op_id": "Table operations > Derive property",
        "output_metadata": [
          {
            "dataframes": {
              "merged": {
                "columns": [
                  "event_subtype",
                  "event_type",
                  "field_pos_abs",
                  "field_pos_rel",
                  "id",
                  "match_event",
                  "match_id",
                  "matchevent_next",
                  "matchevent_seq",
                  "name",
                  "player_id",
                  "team_name",
                  "ts",
                  "x_abs",
                  "x_rel",
                  "y_abs",
                  "y_rel"
                ],
                "key": "merged",
                "length": 125463.0
              }
            },
            "other": {},
            "relations": []
          }
        ],
        "params": {
          "formula": "matchevent_next = matchevent_seq + 1",
          "table_name": "merged"
        },
        "status": "done",
        "telemetry": null,
        "title": "Derive property"
      },
      "height": 315.0,
      "id": "Derive property 2",
      "position": {
        "x": 3896.084834977201,
        "y": 641.3830508020391
      },
      "type": "basic",
      "width": 315.0
    },
    {
      "data": {
        "__execution_delay": 0.0,
        "collapsed": null,
        "display": null,
        "error": null,
        "expanded_height": null,
        "input_metadata": [
          {
            "dataframes": {
              "edges": {
                "columns": [
                  "event_subtype_dst",
                  "event_subtype_src",
                  "event_type_dst",
                  "event_type_src",
                  "field_pos_abs_dst",
                  "field_pos_abs_src",
                  "field_pos_rel_dst",
                  "field_pos_rel_src",
                  "id_dst",
                  "id_src",
                  "match_event_dst",
                  "match_event_src",
                  "match_id_dst",
                  "match_id_src",
                  "matchevent_next_dst",
                  "matchevent_next_src",
                  "matchevent_seq_dst",
                  "matchevent_seq_src",
                  "name_dst",
                  "name_src",
                  "player_id_dst",
                  "player_id_src",
                  "team_name_dst",
                  "team_name_src",
                  "ts_dst",
                  "ts_src",
                  "x_abs_dst",
                  "x_abs_src",
                  "x_rel_dst",
                  "x_rel_src",
                  "y_abs_dst",
                  "y_abs_src",
                  "y_rel_dst",
                  "y_rel_src"
                ],
                "key": "edges",
                "length": 125462.0
              },
              "merged": {
                "columns": [
                  "event_subtype",
                  "event_type",
                  "field_pos_abs",
                  "field_pos_rel",
                  "id",
                  "match_event",
                  "match_id",
                  "matchevent_next",
                  "matchevent_seq",
                  "name",
                  "player_id",
                  "team_name",
                  "ts",
                  "x_abs",
                  "x_rel",
                  "y_abs",
                  "y_rel"
                ],
                "key": "merged",
                "length": 125463.0
              }
            },
            "other": {},
            "relations": [
              {
                "df": "edges",
                "name": "graph",
                "source_column": "matchevent_seq_src",
                "source_key": "matchevent_seq",
                "source_table": "merged",
                "target_column": "matchevent_seq_dst",
                "target_key": "matchevent_seq",
                "target_table": "merged"
              }
            ]
          }
        ],
        "message": null,
        "meta": null,
        "op_id": "Table operations > Filter with formula",
        "output_metadata": [
          {
            "dataframes": {
              "edges": {
                "columns": [
                  "event_subtype_dst",
                  "event_subtype_src",
                  "event_type_dst",
                  "event_type_src",
                  "field_pos_abs_dst",
                  "field_pos_abs_src",
                  "field_pos_rel_dst",
                  "field_pos_rel_src",
                  "id_dst",
                  "id_src",
                  "match_event_dst",
                  "match_event_src",
                  "match_id_dst",
                  "match_id_src",
                  "matchevent_next_dst",
                  "matchevent_next_src",
                  "matchevent_seq_dst",
                  "matchevent_seq_src",
                  "name_dst",
                  "name_src",
                  "player_id_dst",
                  "player_id_src",
                  "team_name_dst",
                  "team_name_src",
                  "ts_dst",
                  "ts_src",
                  "x_abs_dst",
                  "x_abs_src",
                  "x_rel_dst",
                  "x_rel_src",
                  "y_abs_dst",
                  "y_abs_src",
                  "y_rel_dst",
                  "y_rel_src"
                ],
                "key": "edges",
                "length": 113410.0
              },
              "merged": {
                "columns": [
                  "event_subtype",
                  "event_type",
                  "field_pos_abs",
                  "field_pos_rel",
                  "id",
                  "match_event",
                  "match_id",
                  "matchevent_next",
                  "matchevent_seq",
                  "name",
                  "player_id",
                  "team_name",
                  "ts",
                  "x_abs",
                  "x_rel",
                  "y_abs",
                  "y_rel"
                ],
                "key": "merged",
                "length": 125463.0
              }
            },
            "other": {},
            "relations": [
              {
                "df": "edges",
                "name": "graph",
                "source_column": "matchevent_seq_src",
                "source_key": "matchevent_seq",
                "source_table": "merged",
                "target_column": "matchevent_seq_dst",
                "target_key": "matchevent_seq",
                "target_table": "merged"
              }
            ]
          }
        ],
        "params": {
          "formula": "match_id_src == match_id_dst & ts_src + 5 > ts_dst",
          "table_name": "edges"
        },
        "status": "done",
        "telemetry": null,
        "title": "Filter with formula"
      },
      "height": 315.0,
      "id": "Filter with formula 1",
      "position": {
        "x": 5059.010488908439,
        "y": 606.9517877228731
      },
      "type": "basic",
      "width": 315.0
    },
    {
      "data": {
        "__execution_delay": 0.0,
        "collapsed": null,
        "display": null,
        "error": null,
        "expanded_height": null,
        "input_metadata": [
          {
            "dataframes": {
              "edges": {
                "columns": [
                  "event_subtype_dst",
                  "event_subtype_src",
                  "event_type_dst",
                  "event_type_src",
                  "field_pos_abs_dst",
                  "field_pos_abs_src",
                  "field_pos_rel_dst",
                  "field_pos_rel_src",
                  "id_dst",
                  "id_src",
                  "match_event_dst",
                  "match_event_src",
                  "match_id_dst",
                  "match_id_src",
                  "matchevent_next_dst",
                  "matchevent_next_src",
                  "matchevent_seq_dst",
                  "matchevent_seq_src",
                  "name_dst",
                  "name_src",
                  "player_id_dst",
                  "player_id_src",
                  "team_name_dst",
                  "team_name_src",
                  "ts_dst",
                  "ts_src",
                  "x_abs_dst",
                  "x_abs_src",
                  "x_rel_dst",
                  "x_rel_src",
                  "y_abs_dst",
                  "y_abs_src",
                  "y_rel_dst",
                  "y_rel_src"
                ],
                "key": "edges",
                "length": 113410.0
              },
              "merged": {
                "columns": [
                  "event_subtype",
                  "event_type",
                  "field_pos_abs",
                  "field_pos_rel",
                  "id",
                  "match_event",
                  "match_id",
                  "matchevent_next",
                  "matchevent_seq",
                  "name",
                  "player_id",
                  "team_name",
                  "ts",
                  "x_abs",
                  "x_rel",
                  "y_abs",
                  "y_rel"
                ],
                "key": "merged",
                "length": 125463.0
              }
            },
            "other": {},
            "relations": [
              {
                "df": "edges",
                "name": "graph",
                "source_column": "matchevent_seq_src",
                "source_key": "matchevent_seq",
                "source_table": "merged",
                "target_column": "matchevent_seq_dst",
                "target_key": "matchevent_seq",
                "target_table": "merged"
              }
            ]
          }
        ],
        "message": null,
        "meta": null,
        "op_id": "Table operations > Filter with formula",
        "output_metadata": [
          {
            "dataframes": {
              "edges": {
                "columns": [
                  "event_subtype_dst",
                  "event_subtype_src",
                  "event_type_dst",
                  "event_type_src",
                  "field_pos_abs_dst",
                  "field_pos_abs_src",
                  "field_pos_rel_dst",
                  "field_pos_rel_src",
                  "id_dst",
                  "id_src",
                  "match_event_dst",
                  "match_event_src",
                  "match_id_dst",
                  "match_id_src",
                  "matchevent_next_dst",
                  "matchevent_next_src",
                  "matchevent_seq_dst",
                  "matchevent_seq_src",
                  "name_dst",
                  "name_src",
                  "player_id_dst",
                  "player_id_src",
                  "team_name_dst",
                  "team_name_src",
                  "ts_dst",
                  "ts_src",
                  "x_abs_dst",
                  "x_abs_src",
                  "x_rel_dst",
                  "x_rel_src",
                  "y_abs_dst",
                  "y_abs_src",
                  "y_rel_dst",
                  "y_rel_src"
                ],
                "key": "edges",
                "length": 98643.0
              },
              "merged": {
                "columns": [
                  "event_subtype",
                  "event_type",
                  "field_pos_abs",
                  "field_pos_rel",
                  "id",
                  "match_event",
                  "match_id",
                  "matchevent_next",
                  "matchevent_seq",
                  "name",
                  "player_id",
                  "team_name",
                  "ts",
                  "x_abs",
                  "x_rel",
                  "y_abs",
                  "y_rel"
                ],
                "key": "merged",
                "length": 125463.0
              }
            },
            "other": {},
            "relations": [
              {
                "df": "edges",
                "name": "graph",
                "source_column": "matchevent_seq_src",
                "source_key": "matchevent_seq",
                "source_table": "merged",
                "target_column": "matchevent_seq_dst",
                "target_key": "matchevent_seq",
                "target_table": "merged"
              }
            ]
          }
        ],
        "params": {
          "formula": "team_name_src == team_name_dst",
          "table_name": "edges"
        },
        "status": "done",
        "telemetry": null,
        "title": "Filter with formula"
      },
      "height": 315.0,
      "id": "Filter with formula 2",
      "position": {
        "x": 5626.391324979098,
        "y": 629.6470211656995
      },
      "type": "basic",
      "width": 315.0
    },
    {
      "data": {
        "__execution_delay": 0.0,
        "collapsed": null,
        "display": null,
        "error": null,
        "expanded_height": null,
        "input_metadata": [
          {
            "dataframes": {
              "merged": {
                "columns": [
                  "event_subtype",
                  "event_type",
                  "field_pos_abs",
                  "field_pos_rel",
                  "id",
                  "match_event",
                  "match_id",
                  "matchevent_next",
                  "matchevent_seq",
                  "name",
                  "player_id",
                  "team_name",
                  "ts",
                  "x_abs",
                  "x_rel",
                  "y_abs",
                  "y_rel"
                ],
                "key": "merged",
                "length": 125463.0
              }
            },
            "other": {},
            "relations": []
          }
        ],
        "message": null,
        "meta": null,
        "op_id": "Graph operations > Connect nodes on attribute",
        "output_metadata": [
          {
            "dataframes": {
              "edges": {
                "columns": [
                  "event_subtype_dst",
                  "event_subtype_src",
                  "event_type_dst",
                  "event_type_src",
                  "field_pos_abs_dst",
                  "field_pos_abs_src",
                  "field_pos_rel_dst",
                  "field_pos_rel_src",
                  "id_dst",
                  "id_src",
                  "match_event_dst",
                  "match_event_src",
                  "match_id_dst",
                  "match_id_src",
                  "matchevent_next_dst",
                  "matchevent_next_src",
                  "matchevent_seq_dst",
                  "matchevent_seq_src",
                  "name_dst",
                  "name_src",
                  "player_id_dst",
                  "player_id_src",
                  "team_name_dst",
                  "team_name_src",
                  "ts_dst",
                  "ts_src",
                  "x_abs_dst",
                  "x_abs_src",
                  "x_rel_dst",
                  "x_rel_src",
                  "y_abs_dst",
                  "y_abs_src",
                  "y_rel_dst",
                  "y_rel_src"
                ],
                "key": "edges",
                "length": 125462.0
              },
              "merged": {
                "columns": [
                  "event_subtype",
                  "event_type",
                  "field_pos_abs",
                  "field_pos_rel",
                  "id",
                  "match_event",
                  "match_id",
                  "matchevent_next",
                  "matchevent_seq",
                  "name",
                  "player_id",
                  "team_name",
                  "ts",
                  "x_abs",
                  "x_rel",
                  "y_abs",
                  "y_rel"
                ],
                "key": "merged",
                "length": 125463.0
              }
            },
            "other": {},
            "relations": [
              {
                "df": "edges",
                "name": "graph",
                "source_column": "matchevent_seq_src",
                "source_key": "matchevent_seq",
                "source_table": "merged",
                "target_column": "matchevent_seq_dst",
                "target_key": "matchevent_seq",
                "target_table": "merged"
              }
            ]
          }
        ],
        "params": {
          "source_attribute": "matchevent_next",
          "source_id": "matchevent_seq",
          "source_table": "merged",
          "target_attribute": "matchevent_seq",
          "target_id": "matchevent_seq",
          "target_table": "merged"
        },
        "status": "done",
        "telemetry": null,
        "title": "Connect nodes on attribute"
      },
      "height": 606.0,
      "id": "Connect nodes on attribute 1",
      "position": {
        "x": 4291.428804001014,
        "y": 509.78714580247527
      },
      "type": "basic",
      "width": 672.0
    }
  ],
  "paused": null
}
