{
  "edges": [
    {
      "id": "Input: tensor 1 output Concatenate 1 a",
      "source": "Input: tensor 1",
      "sourceHandle": "output",
      "target": "Concatenate 1",
      "targetHandle": "a"
    },
    {
      "id": "Input: tensor 2 output Concatenate 1 b",
      "source": "Input: tensor 2",
      "sourceHandle": "output",
      "target": "Concatenate 1",
      "targetHandle": "b"
    },
    {
      "id": "Concatenate 1 output Linear 1 x",
      "source": "Concatenate 1",
      "sourceHandle": "output",
      "target": "Linear 1",
      "targetHandle": "x"
    },
    {
      "id": "Linear 1 output Activation 1 x",
      "source": "Linear 1",
      "sourceHandle": "output",
      "target": "Activation 1",
      "targetHandle": "x"
    },
    {
      "id": "Linear 2 output Activation 2 x",
      "source": "Linear 2",
      "sourceHandle": "output",
      "target": "Activation 2",
      "targetHandle": "x"
    },
    {
      "id": "Input: tensor 3 output Concatenate 2 a",
      "source": "Input: tensor 3",
      "sourceHandle": "output",
      "target": "Concatenate 2",
      "targetHandle": "a"
    },
    {
      "id": "Input: tensor 4 output Concatenate 2 b",
      "source": "Input: tensor 4",
      "sourceHandle": "output",
      "target": "Concatenate 2",
      "targetHandle": "b"
    },
    {
      "id": "Concatenate 2 output Linear 3 x",
      "source": "Concatenate 2",
      "sourceHandle": "output",
      "target": "Linear 3",
      "targetHandle": "x"
    },
    {
      "id": "Linear 3 output Activation 3 x",
      "source": "Linear 3",
      "sourceHandle": "output",
      "target": "Activation 3",
      "targetHandle": "x"
    },
    {
      "id": "Linear 4 output Activation 4 x",
      "source": "Linear 4",
      "sourceHandle": "output",
      "target": "Activation 4",
      "targetHandle": "x"
    },
    {
      "id": "Linear 5 output Activation 5 x",
      "source": "Linear 5",
      "sourceHandle": "output",
      "target": "Activation 5",
      "targetHandle": "x"
    },
    {
      "id": "Linear 6 output Activation 6 x",
      "source": "Linear 6",
      "sourceHandle": "output",
      "target": "Activation 6",
      "targetHandle": "x"
    },
    {
      "id": "Linear 7 output Output 1 x",
      "source": "Linear 7",
      "sourceHandle": "output",
      "target": "Output 1",
      "targetHandle": "x"
    },
    {
      "id": "Output 1 x Binary cross-entropy with logits loss 1 x",
      "source": "Output 1",
      "sourceHandle": "x",
      "target": "Binary cross-entropy with logits loss 1",
      "targetHandle": "x"
    },
    {
      "id": "Input: tensor 5 output Binary cross-entropy with logits loss 1 y",
      "source": "Input: tensor 5",
      "sourceHandle": "output",
      "target": "Binary cross-entropy with logits loss 1",
      "targetHandle": "y"
    },
    {
      "id": "Binary cross-entropy with logits loss 1 loss Optimizer 1 loss",
      "source": "Binary cross-entropy with logits loss 1",
      "sourceHandle": "loss",
      "target": "Optimizer 1",
      "targetHandle": "loss"
    },
    {
      "id": "Dropout 1 output Linear 2 x",
      "source": "Dropout 1",
      "sourceHandle": "output",
      "target": "Linear 2",
      "targetHandle": "x"
    },
    {
      "id": "Activation 1 output Dropout 1 x",
      "source": "Activation 1",
      "sourceHandle": "output",
      "target": "Dropout 1",
      "targetHandle": "x"
    },
    {
      "id": "Activation 3 output Dropout 2 x",
      "source": "Activation 3",
      "sourceHandle": "output",
      "target": "Dropout 2",
      "targetHandle": "x"
    },
    {
      "id": "Dropout 2 output Linear 4 x",
      "source": "Dropout 2",
      "sourceHandle": "output",
      "target": "Linear 4",
      "targetHandle": "x"
    },
    {
      "id": "Activation 5 output Dropout 3 x",
      "source": "Activation 5",
      "sourceHandle": "output",
      "target": "Dropout 3",
      "targetHandle": "x"
    },
    {
      "id": "Dropout 3 output Linear 6 x",
      "source": "Dropout 3",
      "sourceHandle": "output",
      "target": "Linear 6",
      "targetHandle": "x"
    },
    {
      "id": "Activation 2 output Add 1 a",
      "source": "Activation 2",
      "sourceHandle": "output",
      "target": "Add 1",
      "targetHandle": "a"
    },
    {
      "id": "Activation 4 output Add 1 b",
      "source": "Activation 4",
      "sourceHandle": "output",
      "target": "Add 1",
      "targetHandle": "b"
    },
    {
      "id": "Activation 4 output Subtract 1 b",
      "source": "Activation 4",
      "sourceHandle": "output",
      "target": "Subtract 1",
      "targetHandle": "b"
    },
    {
      "id": "Activation 2 output Subtract 1 a",
      "source": "Activation 2",
      "sourceHandle": "output",
      "target": "Subtract 1",
      "targetHandle": "a"
    },
    {
      "id": "Subtract 1 output Multiply 1 a",
      "source": "Subtract 1",
      "sourceHandle": "output",
      "target": "Multiply 1",
      "targetHandle": "a"
    },
    {
      "id": "Subtract 1 output Multiply 1 b",
      "source": "Subtract 1",
      "sourceHandle": "output",
      "target": "Multiply 1",
      "targetHandle": "b"
    },
    {
      "id": "Activation 2 output Multiply 2 a",
      "source": "Activation 2",
      "sourceHandle": "output",
      "target": "Multiply 2",
      "targetHandle": "a"
    },
    {
      "id": "Activation 4 output Multiply 2 b",
      "source": "Activation 4",
      "sourceHandle": "output",
      "target": "Multiply 2",
      "targetHandle": "b"
    },
    {
      "id": "Add 1 output Concatenate 3 a",
      "source": "Add 1",
      "sourceHandle": "output",
      "target": "Concatenate 3",
      "targetHandle": "a"
    },
    {
      "id": "Multiply 2 output Concatenate 3 b",
      "source": "Multiply 2",
      "sourceHandle": "output",
      "target": "Concatenate 3",
      "targetHandle": "b"
    },
    {
      "id": "Concatenate 3 output Concatenate 4 a",
      "source": "Concatenate 3",
      "sourceHandle": "output",
      "target": "Concatenate 4",
      "targetHandle": "a"
    },
    {
      "id": "Multiply 1 output Concatenate 4 b",
      "source": "Multiply 1",
      "sourceHandle": "output",
      "target": "Concatenate 4",
      "targetHandle": "b"
    },
    {
      "id": "Concatenate 4 output Linear 5 x",
      "source": "Concatenate 4",
      "sourceHandle": "output",
      "target": "Linear 5",
      "targetHandle": "x"
    },
    {
      "id": "Activation 6 output Dropout 4 x",
      "source": "Activation 6",
      "sourceHandle": "output",
      "target": "Dropout 4",
      "targetHandle": "x"
    },
    {
      "id": "Linear 8 output Activation 7 x",
      "source": "Linear 8",
      "sourceHandle": "output",
      "target": "Activation 7",
      "targetHandle": "x"
    },
    {
      "id": "Activation 7 output Linear 7 x",
      "source": "Activation 7",
      "sourceHandle": "output",
      "target": "Linear 7",
      "targetHandle": "x"
    },
    {
      "id": "Dropout 4 output Linear 8 x",
      "source": "Dropout 4",
      "sourceHandle": "output",
      "target": "Linear 8",
      "targetHandle": "x"
    }
  ],
  "env": "PyTorch model",
  "nodes": [
    {
      "data": {
        "__execution_delay": 0.0,
        "display": null,
        "error": null,
        "input_metadata": null,
        "meta": null,
        "op_id": "Input: tensor",
        "params": {
          "name": "product1_embedding",
          "type": "float"
        },
        "status": "done",
        "title": "Input: tensor"
      },
      "dragHandle": ".drag-handle",
      "height": 234.0,
      "id": "Input: tensor 1",
      "position": {
        "x": -253.89521461805123,
        "y": 1079.1526392014362
      },
      "type": "basic",
      "width": 225.0
    },
    {
      "data": {
        "__execution_delay": 0.0,
        "display": null,
        "error": null,
        "input_metadata": null,
        "meta": null,
        "op_id": "Input: tensor",
        "params": {
          "name": "product1_features",
          "type": "float"
        },
        "status": "done",
        "title": "Input: tensor"
      },
      "dragHandle": ".drag-handle",
      "height": 230.0,
      "id": "Input: tensor 2",
      "position": {
        "x": 18.10478538194874,
        "y": 1089.1526392014362
      },
      "type": "basic",
      "width": 302.0
    },
    {
      "data": {
        "collapsed": true,
        "display": null,
        "error": null,
        "input_metadata": null,
        "meta": null,
        "op_id": "Concatenate",
        "params": {},
        "status": "done",
        "title": "Concatenate"
      },
      "dragHandle": ".drag-handle",
      "height": 65.0,
      "id": "Concatenate 1",
      "position": {
        "x": -91.89521461805127,
        "y": 966.1526392014362
      },
      "type": "basic",
      "width": 210.0
    },
    {
      "data": {
        "__execution_delay": 0.0,
        "display": null,
        "error": null,
        "input_metadata": null,
        "meta": null,
        "op_id": "Linear",
        "params": {
          "output_dim": "128"
        },
        "status": "done",
        "title": "Linear"
      },
      "dragHandle": ".drag-handle",
      "height": 152.0,
      "id": "Linear 1",
      "position": {
        "x": -90.75513358727288,
        "y": 742.6897657190082
      },
      "type": "basic",
      "width": 214.0
    },
    {
      "data": {
        "display": null,
        "error": null,
        "input_metadata": null,
        "meta": null,
        "op_id": "Activation",
        "params": {
          "type": "ReLU"
        },
        "status": "done",
        "title": "Activation"
      },
      "dragHandle": ".drag-handle",
      "height": 140.0,
      "id": "Activation 1",
      "position": {
        "x": -93.4088238684672,
        "y": 517.1260918174906
      },
      "type": "basic",
      "width": 207.0
    },
    {
      "data": {
        "__execution_delay": 0.0,
        "display": null,
        "error": null,
        "input_metadata": null,
        "meta": null,
        "op_id": "Linear",
        "params": {
          "output_dim": "64"
        },
        "status": "done",
        "title": "Linear"
      },
      "dragHandle": ".drag-handle",
      "height": 154.0,
      "id": "Linear 2",
      "position": {
        "x": -90.8106997910469,
        "y": 119.28132695348052
      },
      "type": "basic",
      "width": 201.0
    },
    {
      "data": {
        "display": null,
        "error": null,
        "input_metadata": null,
        "meta": null,
        "op_id": "Activation",
        "params": {
          "type": "ReLU"
        },
        "status": "done",
        "title": "Activation"
      },
      "dragHandle": ".drag-handle",
      "height": 142.0,
      "id": "Activation 2",
      "position": {
        "x": -86.95981884472808,
        "y": -90.36020526087106
      },
      "type": "basic",
      "width": 196.0
    },
    {
      "data": {
        "__execution_delay": 0.0,
        "display": null,
        "error": null,
        "input_metadata": null,
        "meta": null,
        "op_id": "Input: tensor",
        "params": {
          "name": "product2_embedding",
          "type": "float"
        },
        "status": "done",
        "title": "Input: tensor"
      },
      "dragHandle": ".drag-handle",
      "height": 214.0,
      "id": "Input: tensor 3",
      "position": {
        "x": 522.247321368616,
        "y": 1106.2453342426306
      },
      "type": "basic",
      "width": 250.0
    },
    {
      "data": {
        "__execution_delay": 0.0,
        "display": null,
        "error": null,
        "input_metadata": null,
        "meta": null,
        "op_id": "Input: tensor",
        "params": {
          "name": "product2_features",
          "type": "float"
        },
        "status": "done",
        "title": "Input: tensor"
      },
      "dragHandle": ".drag-handle",
      "height": 220.0,
      "id": "Input: tensor 4",
      "position": {
        "x": 840.959370942457,
        "y": 1102.9314270598068
      },
      "type": "basic",
      "width": 308.0
    },
    {
      "data": {
        "collapsed": true,
        "display": null,
        "error": null,
        "input_metadata": null,
        "meta": null,
        "op_id": "Concatenate",
        "params": {},
        "status": "done",
        "title": "Concatenate"
      },
      "dragHandle": ".drag-handle",
      "height": 82.0,
      "id": "Concatenate 2",
      "position": {
        "x": 715.0514062560451,
        "y": 977.569955416744
      },
      "type": "basic",
      "width": 208.0
    },
    {
      "data": {
        "__execution_delay": 0.0,
        "display": null,
        "error": null,
        "input_metadata": null,
        "meta": null,
        "op_id": "Linear",
        "params": {
          "output_dim": "128"
        },
        "status": "done",
        "title": "Linear"
      },
      "dragHandle": ".drag-handle",
      "height": 139.0,
      "id": "Linear 3",
      "position": {
        "x": 716.6704099494707,
        "y": 778.5963142144599
      },
      "type": "basic",
      "width": 198.0
    },
    {
      "data": {
        "display": null,
        "error": null,
        "input_metadata": null,
        "meta": null,
        "op_id": "Activation",
        "params": {
          "type": "ReLU"
        },
        "status": "done",
        "title": "Activation"
      },
      "dragHandle": ".drag-handle",
      "height": 139.0,
      "id": "Activation 3",
      "position": {
        "x": 709.5726935909404,
        "y": 558.5671071000235
      },
      "type": "basic",
      "width": 200.0
    },
    {
      "data": {
        "__execution_delay": 0.0,
        "display": null,
        "error": null,
        "input_metadata": null,
        "meta": null,
        "op_id": "Linear",
        "params": {
          "output_dim": "64"
        },
        "status": "done",
        "title": "Linear"
      },
      "dragHandle": ".drag-handle",
      "height": 139.0,
      "id": "Linear 4",
      "position": {
        "x": 702.4139602902534,
        "y": 117.45350919970184
      },
      "type": "basic",
      "width": 211.0
    },
    {
      "data": {
        "display": null,
        "error": null,
        "input_metadata": null,
        "meta": null,
        "op_id": "Activation",
        "params": {
          "type": "ReLU"
        },
        "status": "done",
        "title": "Activation"
      },
      "dragHandle": ".drag-handle",
      "height": 143.0,
      "id": "Activation 4",
      "position": {
        "x": 706.921431761086,
        "y": -97.16041339545222
      },
      "type": "basic",
      "width": 203.0
    },
    {
      "data": {
        "__execution_delay": 0.0,
        "display": null,
        "error": null,
        "input_metadata": null,
        "meta": null,
        "op_id": "Linear",
        "params": {
          "output_dim": "128"
        },
        "status": "done",
        "title": "Linear"
      },
      "dragHandle": ".drag-handle",
      "height": 149.0,
      "id": "Linear 5",
      "position": {
        "x": 314.6800651242934,
        "y": -921.6539837841043
      },
      "type": "basic",
      "width": 211.0
    },
    {
      "data": {
        "display": null,
        "error": null,
        "input_metadata": null,
        "meta": null,
        "op_id": "Activation",
        "params": {
          "type": "ReLU"
        },
        "status": "done",
        "title": "Activation"
      },
      "dragHandle": ".drag-handle",
      "height": 145.0,
      "id": "Activation 5",
      "position": {
        "x": 311.1098772384014,
        "y": -1118.1914852103555
      },
      "type": "basic",
      "width": 213.0
    },
    {
      "data": {
        "display": null,
        "error": null,
        "input_metadata": null,
        "meta": null,
        "op_id": "Activation",
        "params": {
          "type": "ReLU"
        },
        "status": "done",
        "title": "Activation"
      },
      "dragHandle": ".drag-handle",
      "height": 138.0,
      "id": "Activation 6",
      "position": {
        "x": 318.38475902112714,
        "y": -1687.358689880797
      },
      "type": "basic",
      "width": 212.0
    },
    {
      "data": {
        "__execution_delay": 0.0,
        "display": null,
        "error": null,
        "input_metadata": null,
        "meta": null,
        "op_id": "Linear",
        "params": {
          "output_dim": "64"
        },
        "status": "done",
        "title": "Linear"
      },
      "dragHandle": ".drag-handle",
      "height": 137.0,
      "id": "Linear 6",
      "position": {
        "x": 321.229735742707,
        "y": -1487.739991547039
      },
      "type": "basic",
      "width": 199.0
    },
    {
      "data": {
        "__execution_delay": 0.0,
        "display": null,
        "error": null,
        "input_metadata": null,
        "meta": null,
        "op_id": "Linear",
        "params": {
          "output_dim": "1"
        },
        "status": "done",
        "title": "Linear"
      },
      "dragHandle": ".drag-handle",
      "height": 160.0,
      "id": "Linear 7",
      "position": {
        "x": 692.3569255654178,
        "y": -1747.8776713295379
      },
      "type": "basic",
      "width": 219.0
    },
    {
      "data": {
        "__execution_delay": 0.0,
        "display": null,
        "error": null,
        "input_metadata": null,
        "meta": null,
        "op_id": "Output",
        "params": {
          "name": "logit",
          "type": "float"
        },
        "status": "done",
        "title": "Output"
      },
      "dragHandle": ".drag-handle",
      "height": 221.0,
      "id": "Output 1",
      "position": {
        "x": 681.8817439887697,
        "y": -2044.9094121016494
      },
      "type": "basic",
      "width": 244.0
    },
    {
      "data": {
        "__execution_delay": 0.0,
        "display": null,
        "error": null,
        "input_metadata": null,
        "meta": null,
        "op_id": "Input: tensor",
        "params": {
          "name": "label",
          "type": "float"
        },
        "status": "done",
        "title": "Input: tensor"
      },
      "dragHandle": ".drag-handle",
      "height": 212.0,
      "id": "Input: tensor 5",
      "position": {
        "x": 1226.3961898406312,
        "y": -2046.5017971293034
      },
      "type": "basic",
      "width": 257.0
    },
    {
      "data": {
        "display": null,
        "error": null,
        "input_metadata": null,
        "meta": null,
        "op_id": "Binary cross-entropy with logits loss",
        "params": {},
        "status": "done",
        "title": "Binary cross-entropy with logits loss"
      },
      "dragHandle": ".drag-handle",
      "height": 101.0,
      "id": "Binary cross-entropy with logits loss 1",
      "position": {
        "x": 975.7160983317691,
        "y": -2237.718607304132
      },
      "type": "basic",
      "width": 219.0
    },
    {
      "data": {
        "__execution_delay": 0.0,
        "display": null,
        "error": null,
        "input_metadata": null,
        "meta": null,
        "op_id": "Optimizer",
        "params": {
          "lr": "0.0005",
          "type": "AdamW"
        },
        "status": "done",
        "title": "Optimizer"
      },
      "dragHandle": ".drag-handle",
      "height": 228.0,
      "id": "Optimizer 1",
      "position": {
        "x": 963.2204407311476,
        "y": -2541.1845776049445
      },
      "type": "basic",
      "width": 248.0
    },
    {
      "data": {
        "__execution_delay": 0.0,
        "display": null,
        "error": null,
        "input_metadata": null,
        "meta": null,
        "op_id": "Dropout",
        "params": {
          "p": "0.15"
        },
        "status": "done",
        "title": "Dropout"
      },
      "dragHandle": ".drag-handle",
      "height": 152.0,
      "id": "Dropout 1",
      "position": {
        "x": -86.08167796385725,
        "y": 316.7561868224052
      },
      "type": "basic",
      "width": 195.0
    },
    {
      "data": {
        "__execution_delay": 0.0,
        "display": null,
        "error": null,
        "input_metadata": null,
        "meta": null,
        "op_id": "Dropout",
        "params": {
          "p": "0.15"
        },
        "status": "done",
        "title": "Dropout"
      },
      "dragHandle": ".drag-handle",
      "height": 148.0,
      "id": "Dropout 2",
      "position": {
        "x": 695.5766701873247,
        "y": 332.9005933246671
      },
      "type": "basic",
      "width": 226.0
    },
    {
      "data": {
        "__execution_delay": 0.0,
        "display": null,
        "error": null,
        "input_metadata": null,
        "meta": null,
        "op_id": "Dropout",
        "params": {
          "p": "0.15"
        },
        "status": "done",
        "title": "Dropout"
      },
      "dragHandle": ".drag-handle",
      "height": 139.0,
      "id": "Dropout 3",
      "position": {
        "x": 316.49785051249785,
        "y": -1302.8601115531976
      },
      "type": "basic",
      "width": 204.0
    },
    {
      "data": {
        "collapsed": true,
        "display": null,
        "error": null,
        "input_metadata": null,
        "meta": null,
        "op_id": "Add",
        "params": {},
        "status": "done",
        "title": "Add"
      },
      "dragHandle": ".drag-handle",
      "height": 83.0,
      "id": "Add 1",
      "position": {
        "x": 2.3031668039709956,
        "y": -331.7756454856106
      },
      "type": "basic",
      "width": 211.0
    },
    {
      "data": {
        "collapsed": true,
        "display": null,
        "error": null,
        "input_metadata": null,
        "meta": null,
        "op_id": "Subtract",
        "params": {},
        "status": "done",
        "title": "Subtract"
      },
      "dragHandle": ".drag-handle",
      "height": 82.0,
      "id": "Subtract 1",
      "position": {
        "x": 614.8030724852416,
        "y": -340.3249746752126
      },
      "type": "basic",
      "width": 226.0
    },
    {
      "data": {
        "collapsed": true,
        "display": null,
        "error": null,
        "input_metadata": null,
        "meta": null,
        "op_id": "Multiply",
        "params": {},
        "status": "done",
        "title": "Multiply"
      },
      "dragHandle": ".drag-handle",
      "height": 69.0,
      "id": "Multiply 1",
      "position": {
        "x": 574.7566322025082,
        "y": -494.33330937996544
      },
      "type": "basic",
      "width": 189.0
    },
    {
      "data": {
        "collapsed": true,
        "display": null,
        "error": null,
        "input_metadata": null,
        "meta": null,
        "op_id": "Multiply",
        "params": {},
        "status": "done",
        "title": "Multiply"
      },
      "dragHandle": ".drag-handle",
      "height": 60.0,
      "id": "Multiply 2",
      "position": {
        "x": 314.84899481746635,
        "y": -331.2940562891572
      },
      "type": "basic",
      "width": 226.0
    },
    {
      "data": {
        "collapsed": true,
        "display": null,
        "error": null,
        "input_metadata": null,
        "meta": null,
        "op_id": "Concatenate",
        "params": {},
        "status": "done",
        "title": "Concatenate"
      },
      "dragHandle": ".drag-handle",
      "height": 75.0,
      "id": "Concatenate 3",
      "position": {
        "x": 169.1451838394849,
        "y": -489.5102553629112
      },
      "type": "basic",
      "width": 201.0
    },
    {
      "data": {
        "collapsed": true,
        "display": null,
        "error": null,
        "input_metadata": null,
        "meta": null,
        "op_id": "Concatenate",
        "params": {},
        "status": "done",
        "title": "Concatenate"
      },
      "dragHandle": ".drag-handle",
      "height": 61.0,
      "id": "Concatenate 4",
      "position": {
        "x": 319.71018739978035,
        "y": -666.3061341157814
      },
      "type": "basic",
      "width": 207.0
    },
    {
      "data": {
        "__execution_delay": 0.0,
        "display": null,
        "error": null,
        "input_metadata": null,
        "meta": null,
        "op_id": "Dropout",
        "params": {
          "p": "0.15"
        },
        "status": "done",
        "title": "Dropout"
      },
      "dragHandle": ".drag-handle",
      "height": 137.0,
      "id": "Dropout 4",
      "position": {
        "x": 326.6430166081082,
        "y": -1886.161070619254
      },
      "type": "basic",
      "width": 208.0
    },
    {
      "data": {
        "__execution_delay": 0.0,
        "display": null,
        "error": null,
        "input_metadata": null,
        "meta": null,
        "op_id": "Linear",
        "params": {
          "output_dim": "32"
        },
        "status": "done",
        "title": "Linear"
      },
      "dragHandle": ".drag-handle",
      "height": 136.0,
      "id": "Linear 8",
      "position": {
        "x": 701.3224780512727,
        "y": -1298.9118909036295
      },
      "type": "basic",
      "width": 204.0
    },
    {
      "data": {
        "display": null,
        "error": null,
        "input_metadata": null,
        "meta": null,
        "op_id": "Activation",
        "params": {
          "type": "ReLU"
        },
        "status": "done",
        "title": "Activation"
      },
      "dragHandle": ".drag-handle",
      "height": 142.0,
      "id": "Activation 7",
      "position": {
        "x": 704.1545695110068,
        "y": -1508.20018985312
      },
      "type": "basic",
      "width": 198.0
    }
  ],
  "paused": true
}
